helix_platform_api_public_client/__init__.py
helix_platform_api_public_client/api_client.py
helix_platform_api_public_client/api_response.py
helix_platform_api_public_client/configuration.py
helix_platform_api_public_client/exceptions.py
helix_platform_api_public_client/py.typed
helix_platform_api_public_client/rest.py
helix_platform_api_public_client/api/__init__.py
helix_platform_api_public_client/api/attachment_api.py
helix_platform_api_public_client/api/audit_log_api.py
helix_platform_api_public_client/api/default_nomination_api.py
helix_platform_api_public_client/api/manual_file_upload_api.py
helix_platform_api_public_client/api/messages_api.py
helix_platform_api_public_client/api/metadata_api.py
helix_platform_api_public_client/api/nomination_api.py
helix_platform_api_public_client/api/nomination_gate_api.py
helix_platform_api_public_client/api/organisation_api.py
helix_platform_api_public_client/api/participant_dashboard_api.py
helix_platform_api_public_client/api/participant_overview_api.py
helix_platform_api_public_client/api/profile_api.py
helix_platform_api_public_client/api/public_overview_api.py
helix_platform_api_public_client/api/reporting_api.py
helix_platform_api_public_client/api/transmission_right_api.py
helix_platform_api_public_client/api/user_api.py
helix_platform_api_public_client/models/__init__.py
helix_platform_api_public_client/models/aggregated_nomination_options.py
helix_platform_api_public_client/models/aggregated_nomination_options_nominee_participants.py
helix_platform_api_public_client/models/aggregated_nominations.py
helix_platform_api_public_client/models/aggregated_nominations_values.py
helix_platform_api_public_client/models/aggregated_nominations_values_mtus.py
helix_platform_api_public_client/models/aggregated_nominations_values_mtus_netted_nominations.py
helix_platform_api_public_client/models/aggregated_nominations_values_mtus_values.py
helix_platform_api_public_client/models/aggregated_pre_nomination_options.py
helix_platform_api_public_client-1.2.0.dist-info/METADATA
helix_platform_api_public_client-1.2.0.dist-info/WHEEL
helix_platform_api_public_client-1.2.0.dist-info/top_level.txt
helix_platform_api_public_client-1.2.0.dist-info/RECORD
