Metadata-Version: 2.1
Name: helix-platform-api-public-client
Version: 1.2.0
Summary: Platform API
Home-page: 
Author: ElecLink
Author-email: team.eleclink@eleclink.co.uk
Keywords: OpenAPI,OpenAPI-Generator,Platform API
Requires-Dist: pydantic (>=2)
Requires-Dist: python-dateutil (>=2.8.2)
Requires-Dist: typing-extensions (>=4.7.1)
Requires-Dist: urllib3 (<3.0.0,>=1.25.3)
